{
  "id": "fcf-colombia-backend",
  "name": "FCF Colombia Backend",
  "type": "Backend de producto",
  "status": "En desarrollo",
  "progress": 25,
  "repositoryVisibility": "private",
  "repositoryUrl": null,
  "publicDemoUrl": null,
  "techStack": [
    "Spring Boot",
    "PostgreSQL"
  ],
  "summary": "Backend para gestionar equipos, jugadores, partidos, datos deportivos, estadisticas y servicios de la app FCF Colombia.",
  "currentBlock": "Endpoints base y estructura inicial de dominio.",
  "nextStep": "Completar modelos deportivos, endpoints y datos iniciales.",
  "lastCommit": {
    "message": "Pending synchronization",
    "date": "",
    "branch": "main"
  },
  "milestones": [
    {
      "title": "Backend base creado",
      "status": "completed",
      "date": ""
    },
    {
      "title": "Endpoint de equipos por slug",
      "status": "completed",
      "date": ""
    },
    {
      "title": "Estructura inicial de servicios deportivos",
      "status": "in_progress",
      "date": ""
    }
  ],
  "updatedAt": "2026-05-07T16:41:39.1139247-05:00"
}
